.pycheckrc
AUTHORS.rst
CHANGELOG.rst
LICENSE
MANIFEST.in
README.md
pyproject.toml
setup.cfg
setup.py
bpdb/__init__.py
bpdb/__main__.py
bpdb/debugger.py
bpython/__init__.py
bpython/__main__.py
bpython/_internal.py
bpython/_version.py
bpython/args.py
bpython/autocomplete.py
bpython/cli.py
bpython/config.py
bpython/curtsies.py
bpython/filelock.py
bpython/formatter.py
bpython/history.py
bpython/importcompletion.py
bpython/inspection.py
bpython/keys.py
bpython/lazyre.py
bpython/line.py
bpython/pager.py
bpython/paste.py
bpython/patch_linecache.py
bpython/repl.py
bpython/sample-config
bpython/simpleeval.py
bpython/urwid.py
bpython/curtsiesfrontend/__init__.py
bpython/curtsiesfrontend/_internal.py
bpython/curtsiesfrontend/coderunner.py
bpython/curtsiesfrontend/events.py
bpython/curtsiesfrontend/filewatch.py
bpython/curtsiesfrontend/interaction.py
bpython/curtsiesfrontend/interpreter.py
bpython/curtsiesfrontend/manual_readline.py
bpython/curtsiesfrontend/parse.py
bpython/curtsiesfrontend/preprocess.py
bpython/curtsiesfrontend/repl.py
bpython/curtsiesfrontend/replpainter.py
bpython/curtsiesfrontend/sitefix.py
bpython/test/__init__.py
bpython/test/test.config
bpython/test/test.theme
bpython/test/test_args.py
bpython/test/test_autocomplete.py
bpython/test/test_brackets_completion.py
bpython/test/test_config.py
bpython/test/test_crashers.py
bpython/test/test_curtsies.py
bpython/test/test_curtsies_coderunner.py
bpython/test/test_curtsies_painting.py
bpython/test/test_curtsies_parser.py
bpython/test/test_curtsies_repl.py
bpython/test/test_filewatch.py
bpython/test/test_history.py
bpython/test/test_importcompletion.py
bpython/test/test_inspection.py
bpython/test/test_interpreter.py
bpython/test/test_keys.py
bpython/test/test_line_properties.py
bpython/test/test_manual_readline.py
bpython/test/test_preprocess.py
bpython/test/test_repl.py
bpython/test/test_simpleeval.py
bpython/test/fodder/__init__.py
bpython/test/fodder/encoding_ascii.py
bpython/test/fodder/encoding_latin1.py
bpython_django.egg-info/PKG-INFO
bpython_django.egg-info/SOURCES.txt
bpython_django.egg-info/dependency_links.txt
bpython_django.egg-info/entry_points.txt
bpython_django.egg-info/requires.txt
bpython_django.egg-info/top_level.txt
